flowtool_all/__init__.py
flowtool_all/_version.py
flowtool_all-0.7.22.dist-info/DESCRIPTION.rst
flowtool_all-0.7.22.dist-info/METADATA
flowtool_all-0.7.22.dist-info/RECORD
flowtool_all-0.7.22.dist-info/WHEEL
flowtool_all-0.7.22.dist-info/metadata.json
flowtool_all-0.7.22.dist-info/top_level.txt
