Metadata-Version: 2.0
Name: flowtool-all
Version: 0.7.22
Summary: Start managing everything!
Home-page: https://github.com/isnok/py-flowlib
Author: Konstantin Martini
Author-email: k@tuxcode.org
License: UNKNOWN
Keywords: git,flow,commandline,workflow,python,development
Platform: Debian/GNU Linux
Classifier: Development Status :: 3 - Alpha
Classifier: Programming Language :: Python
Classifier: Programming Language :: Python :: 2.7
Classifier: Programming Language :: Python :: 3.3
Classifier: Programming Language :: Python :: 3.4
Classifier: Programming Language :: Python :: 3.5
Classifier: Topic :: System :: Software Distribution
Classifier: Topic :: System :: Systems Administration
Classifier: Topic :: Utilities
Classifier: Intended Audience :: Developers
Classifier: Intended Audience :: System Administrators
Classifier: Operating System :: POSIX
Classifier: Operating System :: Unix
Classifier: Environment :: Console
Requires-Dist: flowtool-base
Requires-Dist: flowtool-git
Requires-Dist: flowtool-gitflow
Requires-Dist: flowtool-githooks
Requires-Dist: flowtool-githooks-demo
Requires-Dist: flowtool-python
Requires-Dist: flowtool-releasing
Requires-Dist: flowtool-stages
Requires-Dist: flowtool-versioning
